kmers_removal/__init__.py
kmers_removal/kmers_removal_launcher.py
test/__init__.py
test/test_kmers_removal_launcher.py
kmers_removal-1.1.3.dist-info/METADATA
kmers_removal-1.1.3.dist-info/WHEEL
kmers_removal-1.1.3.dist-info/entry_points.txt
kmers_removal-1.1.3.dist-info/top_level.txt
kmers_removal-1.1.3.dist-info/RECORD
