Metadata-Version: 2.1
Name: kmers-removal
Version: 1.1.3
Summary: Allows to remove user-specified lists of kmers from a genome assembly
Home-page: https://github.com/GDelevoye/kmers_removal
Author: DELEVOYE Guillaume
Author-email: delevoye@ens.fr
Requires-Python: >=3
Requires-Dist: pandas
Requires-Dist: tqdm
